.project
.pydevproject
LICENSE.txt
README.txt
bootstrap.py
buildout.cfg
setup.py
src/bda/__init__.py
src/bda.zeopack.egg-info/PKG-INFO
src/bda.zeopack.egg-info/SOURCES.txt
src/bda.zeopack.egg-info/dependency_links.txt
src/bda.zeopack.egg-info/entry_points.txt
src/bda.zeopack.egg-info/namespace_packages.txt
src/bda.zeopack.egg-info/not-zip-safe
src/bda.zeopack.egg-info/requires.txt
src/bda.zeopack.egg-info/top_level.txt
src/bda/zeopack/__init__.py
src/bda/zeopack/common.py
src/bda/zeopack/main.py