Metadata-Version: 1.0
Name: bda.zeopack
Version: 1.0
Summary: Pack (multiple) databases (ZODB) on Zope ZEO servers
Home-page: http://pypi.python.org/pypi/bda.zeopack
Author: Jens W. Klein
Author-email: jens@bluedynamics.com
License: BSD License
Platform: UNKNOWN
Classifier: Framework :: ZODB
Classifier: Operating System :: OS Independent
Classifier: Programming Language :: Python
Classifier: License :: OSI Approved :: BSD License
